setup.py
intentBox/__init__.py
intentBox/box.py
intentBox/container.py
intentBox/segmenter.py
intentBox.egg-info/PKG-INFO
intentBox.egg-info/SOURCES.txt
intentBox.egg-info/dependency_links.txt
intentBox.egg-info/requires.txt
intentBox.egg-info/top_level.txt
intentBox/coreference/__init__.py
intentBox/coreference/base.py
intentBox/coreference/pronoun_postags.py
intentBox/coreference/remote.py
intentBox/intent_assistant/__init__.py
intentBox/intent_assistant/collision_detector.py
intentBox/lang/__init__.py
intentBox/lang/en.py
intentBox/lang/pt.py
intentBox/parsers/__init__.py
intentBox/parsers/adapt_extract.py
intentBox/parsers/nebulento_extract.py
intentBox/parsers/padacioso_extract.py
intentBox/parsers/padaos_extract.py
intentBox/parsers/padatious_extract.py
intentBox/parsers/palavreado_extract.py
intentBox/parsers/template.py
intentBox/segmentation/__init__.py
intentBox/segmentation/simple.py
intentBox/utils/__init__.py
intentBox/utils/bracket_expansion.py
intentBox/utils/log.py
test/test_adapt.py
test/test_box.py
test/test_nebuloso.py
test/test_padacioso.py
test/test_padaos.py
test/test_padatious.py
test/test_palavreado.py
test/test_regex.py
test/test_strategy.py
test/test_utils.py