Metadata-Version: 2.1
Name: intentBox
Version: 0.3.0a3
Summary: chatterbox intent parser, extract multiple intents from a single utterance 
Home-page: https://github.com/HelloChatterbox/intentBox
Author: jarbasai
Author-email: jarbasai@mailfence.com
License: UNKNOWN
Platform: UNKNOWN
Provides-Extra: extras
